cripto/__init__.py
cripto/cifrador_core.py
cripto/generador_key.py
cripto/test.py
cripto_learn-0.1.0.dist-info/licenses/LICENSE
cripto_learn-0.1.0.dist-info/METADATA
cripto_learn-0.1.0.dist-info/WHEEL
cripto_learn-0.1.0.dist-info/top_level.txt
cripto_learn-0.1.0.dist-info/RECORD
