Metadata-Version: 2.4
Name: cripto-learn
Version: 0.1.0
Summary: Encryption/decryption library (Feistel-CBC) capable of encrypting files, directories, and databases, created as a test for learning cryptography
Home-page: https://github.com/Nooch98/cripto
Author: Nooch98
Author-email: 
Classifier: Development Status :: 3 - Alpha
Classifier: Intended Audience :: Developers
Classifier: License :: OSI Approved :: MIT License
Classifier: Programming Language :: Python :: 3
Classifier: Programming Language :: Python :: 3.8
Classifier: Programming Language :: Python :: 3.9
Classifier: Programming Language :: Python :: 3.10
Requires-Python: >=3.8
License-File: LICENSE
Dynamic: author
Dynamic: classifier
Dynamic: description
Dynamic: description-content-type
Dynamic: home-page
Dynamic: license-file
Dynamic: requires-python
Dynamic: summary
